feedback_grape/__init__.py
feedback_grape/fgrape.py
feedback_grape/grape.py
feedback_grape/py.typed
feedback_grape/utils/__init__.py
feedback_grape/utils/fgrape_helpers.py
feedback_grape/utils/fidelity.py
feedback_grape/utils/gates.py
feedback_grape/utils/modeling.py
feedback_grape/utils/operators.py
feedback_grape/utils/optimizers.py
feedback_grape/utils/povm.py
feedback_grape/utils/purity.py
feedback_grape/utils/py.typed
feedback_grape/utils/solver.py
feedback_grape/utils/states.py
feedback_grape/utils/superoperator.py
feedback_grape/utils/tensor.py
feedback_grape-0.0.1rc2.dist-info/licenses/LICENSE
feedback_grape-0.0.1rc2.dist-info/METADATA
feedback_grape-0.0.1rc2.dist-info/WHEEL
feedback_grape-0.0.1rc2.dist-info/top_level.txt
feedback_grape-0.0.1rc2.dist-info/RECORD
