Metadata-Version: 2.4
Name: feedback_grape
Version: 0.0.1rc2
Summary: A package for GRAPE with feedback
Author: Yousef Elbrolosy
Author-email: yousef.elbrolosy@mpl.mpg.de
License: MIT
Platform: any
Classifier: Development Status :: 4 - Beta
Classifier: Intended Audience :: Science/Research
Classifier: License :: OSI Approved :: MIT License
Classifier: Operating System :: OS Independent
Classifier: Programming Language :: Python
Classifier: Programming Language :: Python :: 3
Classifier: Programming Language :: Python :: 3.11
Classifier: Topic :: Scientific/Engineering
Requires-Python: >=3.11
License-File: LICENSE
Requires-Dist: numpy>=2.2.4
Requires-Dist: scipy>=1.15.2
Requires-Dist: matplotlib>=3.10.1
Requires-Dist: jax==0.5.2
Requires-Dist: chex==0.1.89
Requires-Dist: optax==0.2.4
Requires-Dist: flax==0.10.6
Requires-Dist: dynamiqs==0.3.2
Provides-Extra: testing
Requires-Dist: pytest; extra == "testing"
Requires-Dist: mypy; extra == "testing"
Requires-Dist: ruff; extra == "testing"
Provides-Extra: cuda12
Requires-Dist: jax[cuda12]==0.5.2; extra == "cuda12"
Dynamic: description
Dynamic: description-content-type
Dynamic: license-file
